{
  "source_file": "ljx_12.txt",
  "job_title": "后端开发工程师",
  "location": "北京、上海",
  "education": "本科",
  "experience": "不限",
  "employment_type": "全职",
  "job_category": "后端开发",
  "job_sub_category": "高并发、分布式系统、微服务",
  "company_name": "快手",
  "workmode": "现场",
  "responsibilities": [
    "负责快手核心产品（短视频、直播、电商）后端系统设计与开发",
    "参与高并发场景下的架构设计，保障系统稳定性和高性能",
    "负责内容推荐、用户增长、支付交易等核心服务的开发与优化",
    "推动微服务架构改造，提升系统可维护性和研发效率",
    "参与大模型应用、内容理解等AI技术的工程化落地"
  ],
  "required_skills": [
    {
      "name": "Go",
      "proficiency": "熟练",
      "proficiency_rank": 3,
      "category": "编程语言",
      "skill_type": "hard"
    },
    {
      "name": "Java",
      "proficiency": "熟练",
      "proficiency_rank": 3,
      "category": "编程语言",
      "skill_type": "hard"
    },
    {
      "name": "C++",
      "proficiency": "熟练",
      "proficiency_rank": 3,
      "category": "编程语言",
      "skill_type": "hard"
    },
    {
      "name": "高并发系统开发",
      "proficiency": "不限",
      "category": "架构模式",
      "skill_type": "hard"
    },
    {
      "name": "Linux",
      "proficiency": "熟悉",
      "proficiency_rank": 2,
      "category": "操作系统",
      "skill_type": "hard"
    },
    {
      "name": "Shell",
      "proficiency": "熟练",
      "proficiency_rank": 3,
      "category": "编程语言",
      "skill_type": "hard"
    },
    {
      "name": "Git",
      "proficiency": "熟练",
      "proficiency_rank": 3,
      "category": "版本控制",
      "skill_type": "hard"
    },
    {
      "name": "MySQL",
      "proficiency": "不限",
      "category": "数据库",
      "skill_type": "hard"
    },
    {
      "name": "Redis",
      "proficiency": "不限",
      "category": "缓存",
      "skill_type": "hard"
    },
    {
      "name": "Kafka",
      "proficiency": "不限",
      "category": "消息队列",
      "skill_type": "hard"
    },
    {
      "name": "问题分析和解决能力",
      "proficiency": "良好",
      "category": "软技能",
      "skill_type": "soft"
    },
    {
      "name": "线上问题定位",
      "proficiency": "不限",
      "category": "通用技能",
      "skill_type": "hard"
    }
  ],
  "preferred_skills": [
    {
      "name": "分布式存储",
      "proficiency": "了解",
      "proficiency_rank": 1,
      "category": "大数据",
      "skill_type": "hard"
    },
    {
      "name": "容器化",
      "proficiency": "了解",
      "proficiency_rank": 1,
      "category": "容器与编排",
      "skill_type": "hard"
    },
    {
      "name": "Kubernetes",
      "proficiency": "了解",
      "proficiency_rank": 1,
      "category": "容器与编排",
      "skill_type": "hard"
    },
    {
      "name": "机器学习",
      "proficiency": "了解",
      "proficiency_rank": 1,
      "category": "机器学习",
      "skill_type": "hard"
    },
    {
      "name": "特征工程",
      "proficiency": "了解",
      "proficiency_rank": 1,
      "category": "机器学习",
      "skill_type": "hard"
    },
    {
      "name": "模型服务化",
      "proficiency": "了解",
      "proficiency_rank": 1,
      "category": "机器学习",
      "skill_type": "hard"
    },
    {
      "name": "短视频",
      "proficiency": "了解",
      "proficiency_rank": 1,
      "category": "其他",
      "skill_type": "domain"
    },
    {
      "name": "直播",
      "proficiency": "了解",
      "proficiency_rank": 1,
      "category": "其他",
      "skill_type": "domain"
    },
    {
      "name": "电商",
      "proficiency": "了解",
      "proficiency_rank": 1,
      "category": "其他",
      "skill_type": "domain"
    },
    {
      "name": "推荐系统",
      "proficiency": "不限",
      "category": "机器学习",
      "skill_type": "domain"
    },
    {
      "name": "内容理解",
      "proficiency": "不限",
      "category": "AI工具",
      "skill_type": "domain"
    },
    {
      "name": "开源项目贡献",
      "proficiency": "不限",
      "category": "通用技能",
      "skill_type": "soft"
    },
    {
      "name": "技术博客撰写",
      "proficiency": "不限",
      "category": "通用技能",
      "skill_type": "soft"
    }
  ],
  "raw_requirements": [
    "必须具备的：",
    "本科及以上学历，计算机、软件工程等相关专业；",
    "熟练掌握Go/Java/C++等至少一门后端语言，有高并发系统开发经验；",
    "熟悉Linux操作系统，熟练使用Shell、Git等工具；",
    "掌握MySQL、Redis、Kafka等常用组件原理与应用；",
    "具备良好的问题分析和解决能力，能快速定位线上问题。有一定了解的：",
    "分布式存储、容器化、K8s编排技术；",
    "机器学习基础，了解特征工程、模型服务化流程；",
    "短视频/直播/电商业务逻辑。"
  ]
}